aiodec.py
aiodec-2018.10.1.dist-info/LICENSE
aiodec-2018.10.1.dist-info/WHEEL
aiodec-2018.10.1.dist-info/METADATA
aiodec-2018.10.1.dist-info/RECORD
