Metadata-Version: 2.1
Name: aiodec
Version: 2018.10.1
Summary: aiodec
Home-page: https://github.com/cjrh/aiodec
License: UNKNOWN
Author: Caleb Hattingh
Author-email: caleb.hattingh@gmail.com
Classifier: License :: OSI Approved :: Apache Software License
Classifier: Natural Language :: English
Classifier: Programming Language :: Python
Classifier: Programming Language :: Python :: 3.6
Classifier: Programming Language :: Python :: 3.7
Classifier: Operating System :: OS Independent
Requires-Dist: pytest; extra == "dev"
Requires-Dist: pytest-cov; extra == "dev"
Requires-Dist: wheel; extra == "dev"
Requires-Dist: coveralls; extra == "dev"
Provides-Extra: dev
